setup.py
PyAParser.egg-info/PKG-INFO
PyAParser.egg-info/SOURCES.txt
PyAParser.egg-info/dependency_links.txt
PyAParser.egg-info/not-zip-safe
PyAParser.egg-info/top_level.txt
aparser/__init__.py