Metadata-Version: 1.1
Name: PyAParser
Version: 0.1
Summary: Python library for working with AParser API
Home-page: https://github.com/kronas/PyAParser
Author: Kronas
Author-email: kronas.sw@gmail.com
License: MIT
Platform: UNKNOWN
Classifier: Development Status :: 3 - Alpha
Classifier: Intended Audience :: Developers
Classifier: License :: OSI Approved :: MIT License
Classifier: Natural Language :: English
Classifier: Operating System :: OS Independent
Classifier: Programming Language :: Python :: 2
Classifier: Topic :: Software Development :: Libraries :: Python Modules
